Metadata-Version: 2.1
Name: pacote-teste-classic
Version: 0.0.1
Summary: UNKNOWN
License: UNKNOWN
Platform: UNKNOWN
License-File: LICENSE
Requires-Dist: httpx
